cubats-1.0.0.dist-info/METADATA
cubats-1.0.0.dist-info/WHEEL
cubats-1.0.0.dist-info/entry_points.txt
cubats-1.0.0.dist-info/licenses/LICENSE.txt
cubats/.DS_Store
cubats/Main.ipynb
cubats/__init__.py
cubats/assets/antigen_profiles.json
cubats/assets/ref_norm.png
cubats/config.py
cubats/cutils.py
cubats/logging_config.py
cubats/logs/cubats.log
cubats/logs/cubats.log.1
cubats/slide_collection/.DS_Store
cubats/slide_collection/__init__.py
cubats/slide_collection/registration.py
cubats/slide_collection/segmentation.py
cubats/slide_collection/slide.py
cubats/slide_collection/slide_collection.py
cubats/slide_collection/tile_colocalization.py
cubats/slide_collection/tile_quantification.py
cubats-1.0.0.dist-info/RECORD
