Metadata-Version: 2.1
Name: CuBATS
Version: 1.0.0
Summary: Computer vision-Based Antigen Target Selector
Keywords: digital pathology,whole-slide imaging,patient-specific antigen analysis,spatial antigen heterogeneity
Author-Email: Moritz Dinser <moritz.dinser@hnu.de>, Daniel Hieber <daniel.hieber@hnu.de>
License: MIT
Classifier: Development Status :: 5 - Production/Stable
Classifier: Intended Audience :: Developers
Classifier: Intended Audience :: Science/Research
Classifier: Intended Audience :: Healthcare Industry
Classifier: Operating System :: MacOS :: MacOS X
Classifier: Operating System :: Microsoft :: Windows
Classifier: Operating System :: POSIX :: Linux
Classifier: License :: OSI Approved :: MIT License
Classifier: Programming Language :: Python
Classifier: Programming Language :: Python :: 3
Classifier: Programming Language :: Python :: 3.10
Classifier: Programming Language :: Python :: 3.11
Classifier: Topic :: Scientific/Engineering :: Artificial Intelligence
Classifier: Topic :: Scientific/Engineering :: Image Processing
Classifier: Topic :: Scientific/Engineering :: Image Recognition
Classifier: Topic :: Scientific/Engineering :: Medical Science Apps.
Classifier: Topic :: Scientific/Engineering :: Bio-Informatics
Project-URL: Repository, https://github.com/hnu-digihealth/CuBATS
Project-URL: Documentation, https://hnu-digihealth.github.io/CuBATS/
Requires-Python: <3.12,>=3.10
Requires-Dist: openslide-python>=1.3
Requires-Dist: valis-wsi>=1.0
Requires-Dist: onnx>=1.16
Requires-Dist: onnx2torch==1.5
Requires-Dist: torchvision>=0.20
Requires-Dist: torchstain>=1.3
Requires-Dist: numpy==1.26.4
Requires-Dist: array-api-compat>=1.11.2
Requires-Dist: onnxruntime-gpu>=1.10; sys_platform == "win32"
Requires-Dist: cupy-cuda12x>=13.3; sys_platform == "win32"
